LICENSE
MANIFEST.in
README.rst
requirements.txt
setup.py
django_ar_organizations.egg-info/PKG-INFO
django_ar_organizations.egg-info/SOURCES.txt
django_ar_organizations.egg-info/dependency_links.txt
django_ar_organizations.egg-info/not-zip-safe
django_ar_organizations.egg-info/requires.txt
django_ar_organizations.egg-info/top_level.txt
organizations/__init__.py
organizations/admin.py
organizations/app_settings.py
organizations/decorators.py
organizations/exceptions.py
organizations/forms.py
organizations/managers.py
organizations/mixins.py
organizations/models.py
organizations/urls.py
organizations/utils.py
organizations/views.py
organizations/backends/__init__.py
organizations/backends/defaults.py
organizations/backends/forms.py
organizations/backends/tokens.py
organizations/fixtures/orgs.json
organizations/fixtures/users.json
organizations/middleware/__init__.py
organizations/migrations/0001_initial.py
organizations/migrations/0002_auto_20150420_1420.py
organizations/migrations/0003_auto_20150420_1425.py
organizations/migrations/0004_auto_20170531_1321.py
organizations/migrations/__init__.py
organizations/templates/organizations_base.html
organizations/templates/organizations/login.html
organizations/templates/organizations/myorgs.html
organizations/templates/organizations/organization_confirm_delete.html
organizations/templates/organizations/organization_detail.html
organizations/templates/organizations/organization_form.html
organizations/templates/organizations/organization_list.html
organizations/templates/organizations/organization_switch.html
organizations/templates/organizations/organization_switch_error.html
organizations/templates/organizations/organization_users.html
organizations/templates/organizations/organizationuser_confirm_delete.html
organizations/templates/organizations/organizationuser_detail.html
organizations/templates/organizations/organizationuser_form.html
organizations/templates/organizations/organizationuser_list.html
organizations/templates/organizations/organizationuser_remind.html
organizations/templates/organizations/register_form.html
organizations/templates/organizations/register_success.html
organizations/templates/organizations/email/activation_body.html
