Metadata-Version: 1.1
Name: django-ar-organizations
Version: 0.2.42
Summary: Group accounts for Django
Home-page: https://github.com/arteria/django-ar-organizations/
Author: Ben Lopatin + arteria GmbH
Author-email: ben.lopatin@wellfireinteractive.com
License: BSD License
Platform: OS Independent
Classifier: Development Status :: 4 - Beta
Classifier: Framework :: Django
Classifier: Environment :: Web Environment
Classifier: Intended Audience :: Developers
Classifier: License :: OSI Approved :: BSD License
Classifier: Operating System :: OS Independent
Classifier: Natural Language :: English
Classifier: Programming Language :: Python
Classifier: Programming Language :: Python :: 2.7
Classifier: Programming Language :: Python :: 3.4
